bimdata_api_client/__init__.py
bimdata_api_client/api_client.py
bimdata_api_client/configuration.py
bimdata_api_client/exceptions.py
bimdata_api_client/model_utils.py
bimdata_api_client/rest.py
bimdata_api_client/api/__init__.py
bimdata_api_client/api/bcf_api.py
bimdata_api_client/api/collaboration_api.py
bimdata_api_client/api/ifc_api.py
bimdata_api_client/api/model_api.py
bimdata_api_client/api/sso_api.py
bimdata_api_client/api/webhook_api.py
bimdata_api_client/apis/__init__.py
bimdata_api_client/model/__init__.py
bimdata_api_client/model/auth.py
bimdata_api_client/model/bcf_project.py
bimdata_api_client/model/bcf_project_request.py
bimdata_api_client/model/building.py
bimdata_api_client/model/building_model_plan_request.py
bimdata_api_client/model/check_project_access.py
bimdata_api_client/model/classification.py
bimdata_api_client/model/classification_request.py
bimdata_api_client/model/clipping_plane.py
bimdata_api_client/model/clipping_plane_request.py
bimdata_api_client/model/cloud.py
bimdata_api_client/model/cloud_invitation.py
bimdata_api_client/model/cloud_invitation_request.py
bimdata_api_client/model/cloud_request.py
bimdata_api_client/model/cloud_role.py
bimdata_api_client/model/coloring.py
bimdata_api_client/model/coloring_request.py
bimdata_api_client/model/comment.py
bimdata_api_client/model/comment_request.py
bimdata_api_client/model/component.py
bimdata_api_client/model/component_request.py
bimdata_api_client/model/components_parent.py
bimdata_api_client/model/components_parent_request.py
bimdata_api_client/model/create_building_by_name_request.py
bimdata_api_client/model/create_model_request.py
bimdata_api_client/model/create_multi_page_model_request.py
bimdata_api_client/model/create_user_request.py
bimdata_api_client/model/detailed_extensions.py
bimdata_api_client/model/direction.py
bimdata_api_client/model/direction_request.py
bimdata_api_client/model/document.py
bimdata_api_client/model/document_preview_file.py
bimdata_api_client-9.22.1.dist-info/METADATA
bimdata_api_client-9.22.1.dist-info/WHEEL
bimdata_api_client-9.22.1.dist-info/top_level.txt
bimdata_api_client-9.22.1.dist-info/RECORD
