Metadata-Version: 2.1
Name: bimdata-api-client
Version: 9.22.1
Summary: BIMData API
Home-page: https://github.com/bimdata/python-api-client
Author: BIMData.io
Author-email: contact@bimdata.io
License: UNKNOWN
Keywords: Swagger,BIMData API
Platform: UNKNOWN
Requires-Dist: certifi >=14.05.14
Requires-Dist: six >=1.10
Requires-Dist: python-dateutil >=2.5.3
Requires-Dist: setuptools >=21.0.0
Requires-Dist: urllib3 >=1.15.1
